ismartgate/__init__.py
ismartgate/cli.py
ismartgate/common.py
ismartgate/const.py
ismartgate/tests/__init__.py
ismartgate/tests/common.py
ismartgate/tests/test_cli.py
ismartgate/tests/test_common.py
ismartgate/tests/test_init.py
ismartgate-5.0.1.dist-info/LICENSE
ismartgate-5.0.1.dist-info/METADATA
ismartgate-5.0.1.dist-info/WHEEL
ismartgate-5.0.1.dist-info/entry_points.txt
ismartgate-5.0.1.dist-info/top_level.txt
ismartgate-5.0.1.dist-info/RECORD
