Metadata-Version: 2.1
Name: ismartgate
Version: 5.0.1
Summary: iSmartGate and GogoGate2 API
Home-page: https://github.com/bdraco/ismartgate
Author: Robbie Van Gorkom; J. Nick Koston
Author-email: nick@koston.org
License: MIT license
Keywords: ismartgate
Classifier: Development Status :: 2 - Pre-Alpha
Classifier: Intended Audience :: Developers
Classifier: License :: OSI Approved :: MIT License
Classifier: Natural Language :: English
Classifier: Programming Language :: Python :: 3.8
Classifier: Programming Language :: Python :: 3.9
Classifier: Programming Language :: Python :: 3.10
Classifier: Programming Language :: Python :: 3.11
Requires-Python: >=3.8
License-File: LICENSE
Requires-Dist: dicttoxml >=1.7.4
Requires-Dist: defusedxml >=0.7.1
Requires-Dist: pycryptodome >=3.9.8
Requires-Dist: httpx >=0.18.0
Provides-Extra: all
Requires-Dist: dicttoxml >=1.7.4 ; extra == 'all'
Requires-Dist: defusedxml >=0.7.1 ; extra == 'all'
Requires-Dist: pycryptodome >=3.9.8 ; extra == 'all'
Requires-Dist: httpx >=0.18.0 ; extra == 'all'
Requires-Dist: pytest-runner >=5.2 ; extra == 'all'
Requires-Dist: typing-extensions >=3.10.0.0 ; extra == 'all'
Requires-Dist: respx >=0.17.0 ; extra == 'all'
Requires-Dist: pytest-asyncio ; extra == 'all'
Requires-Dist: black >=22.12.0 ; extra == 'all'
Requires-Dist: codecov >=2.1.4 ; extra == 'all'
Requires-Dist: flake8 >=3.8.3 ; extra == 'all'
Requires-Dist: flake8-debugger >=3.2.1 ; extra == 'all'
Requires-Dist: pytest >=5.4.3 ; extra == 'all'
Requires-Dist: pytest-cov >=2.9.0 ; extra == 'all'
Requires-Dist: pytest-raises >=0.11 ; extra == 'all'
Requires-Dist: bump2version >=1.0.1 ; extra == 'all'
Requires-Dist: coverage >=5.1 ; extra == 'all'
Requires-Dist: ipython >=7.15.0 ; extra == 'all'
Requires-Dist: m2r2 >=0.2.7 ; extra == 'all'
Requires-Dist: Sphinx >=3.4.3 ; extra == 'all'
Requires-Dist: sphinx-rtd-theme >=0.5.1 ; extra == 'all'
Requires-Dist: tox >=3.15.2 ; extra == 'all'
Requires-Dist: twine >=3.1.1 ; extra == 'all'
Requires-Dist: wheel >=0.34.2 ; extra == 'all'
Provides-Extra: dev
Requires-Dist: pytest-runner >=5.2 ; extra == 'dev'
Requires-Dist: typing-extensions >=3.10.0.0 ; extra == 'dev'
Requires-Dist: respx >=0.17.0 ; extra == 'dev'
Requires-Dist: pytest-asyncio ; extra == 'dev'
Requires-Dist: black >=22.12.0 ; extra == 'dev'
Requires-Dist: codecov >=2.1.4 ; extra == 'dev'
Requires-Dist: flake8 >=3.8.3 ; extra == 'dev'
Requires-Dist: flake8-debugger >=3.2.1 ; extra == 'dev'
Requires-Dist: pytest >=5.4.3 ; extra == 'dev'
Requires-Dist: pytest-cov >=2.9.0 ; extra == 'dev'
Requires-Dist: pytest-raises >=0.11 ; extra == 'dev'
Requires-Dist: bump2version >=1.0.1 ; extra == 'dev'
Requires-Dist: coverage >=5.1 ; extra == 'dev'
Requires-Dist: ipython >=7.15.0 ; extra == 'dev'
Requires-Dist: m2r2 >=0.2.7 ; extra == 'dev'
Requires-Dist: Sphinx >=3.4.3 ; extra == 'dev'
Requires-Dist: sphinx-rtd-theme >=0.5.1 ; extra == 'dev'
Requires-Dist: tox >=3.15.2 ; extra == 'dev'
Requires-Dist: twine >=3.1.1 ; extra == 'dev'
Requires-Dist: wheel >=0.34.2 ; extra == 'dev'
Provides-Extra: setup
Requires-Dist: pytest-runner >=5.2 ; extra == 'setup'
Provides-Extra: test
Requires-Dist: typing-extensions >=3.10.0.0 ; extra == 'test'
Requires-Dist: respx >=0.17.0 ; extra == 'test'
Requires-Dist: pytest-asyncio ; extra == 'test'
Requires-Dist: black >=22.12.0 ; extra == 'test'
Requires-Dist: codecov >=2.1.4 ; extra == 'test'
Requires-Dist: flake8 >=3.8.3 ; extra == 'test'
Requires-Dist: flake8-debugger >=3.2.1 ; extra == 'test'
Requires-Dist: pytest >=5.4.3 ; extra == 'test'
Requires-Dist: pytest-cov >=2.9.0 ; extra == 'test'
Requires-Dist: pytest-raises >=0.11 ; extra == 'test'
